{
    "collaborative": false,
    "description": "first playlist creation via python",
    "external_urls": {
        "spotify": "https://open.spotify.com/playlist/2HmhNvm82A0qgKykN4OSSy"
    },
    "followers": {
        "href": null,
        "total": 0
    },
    "href": "https://api.spotify.com/v1/playlists/2HmhNvm82A0qgKykN4OSSy",
    "id": "2HmhNvm82A0qgKykN4OSSy",
    "images": [],
    "name": "Test",
    "owner": {
        "display_name": "Atomdonat",
        "external_urls": {
            "spotify": "https://open.spotify.com/user/simonluca1"
        },
        "href": "https://api.spotify.com/v1/users/simonluca1",
        "id": "simonluca1",
        "type": "user",
        "uri": "spotify:user:simonluca1"
    },
    "primary_color": null,
    "public": false,
    "snapshot_id": "MSw1MDBhZmIwZTg4NjRlM2NlYzcyOTU5YTg0MmUwNTA4ZDZhZmEzZGZi",
    "tracks": {
        "href": "https://api.spotify.com/v1/playlists/2HmhNvm82A0qgKykN4OSSy/tracks",
        "items": [],
        "limit": 100,
        "next": null,
        "offset": 0,
        "previous": null,
        "total": 0
    },
    "type": "playlist",
    "uri": "spotify:playlist:2HmhNvm82A0qgKykN4OSSy"
}